cube_dl/__init__.py
cube_dl/c3lyr/__init__.py
cube_dl/c3lyr/dao.py
cube_dl/c3lyr/dao_json_impl.py
cube_dl/c3lyr/entities.py
cube_dl/c3lyr/run_context.py
cube_dl/callback.py
cube_dl/cli/__init__.py
cube_dl/cli/subcmd_add_exp.py
cube_dl/cli/subcmd_ls.py
cube_dl/cli/subcmd_new.py
cube_dl/cli/subcmd_rm.py
cube_dl/cli/subcmd_start.py
cube_dl/cli/subcmd_version.py
cube_dl/cli/subcmds_exec.py
cube_dl/cli/utils.py
cube_dl/config_sys/__init__.py
cube_dl/config_sys/config_decorators.py
cube_dl/config_sys/root_config.py
cube_dl/config_sys/shared_config.py
cube_dl/core/__init__.py
cube_dl/core/components.py
cube_dl/main.py
cube_dl/utils.py
cube_dl-0.3.10.dist-info/LICENSE
cube_dl-0.3.10.dist-info/METADATA
cube_dl-0.3.10.dist-info/WHEEL
cube_dl-0.3.10.dist-info/entry_points.txt
cube_dl-0.3.10.dist-info/RECORD
