Metadata-Version: 2.1
Name: cube-dl
Version: 0.3.10
Summary: "The last stop" for training your deep learning models. Manage tons of configurations and experiments with minimal changes to existing code.
License: GPL-3.0-or-later
Keywords: python,data-science,machine-learning,deep-learning,python3,pytorch,pytorch-lightning
Author: Alive1024
Author-email: 2431945058@qq.com
Requires-Python: >=3.10,<4.0
Classifier: Development Status :: 3 - Alpha
Classifier: License :: OSI Approved :: GNU General Public License v3 or later (GPLv3+)
Classifier: Operating System :: MacOS
Classifier: Operating System :: Unix
Classifier: Programming Language :: Python :: 3
Classifier: Programming Language :: Python :: 3.10
Classifier: Programming Language :: Python :: 3.11
Classifier: Programming Language :: Python :: 3.12
Classifier: Programming Language :: Python :: 3 :: Only
Requires-Dist: jsonpath-ng (>=1.5.3,<2.0.0)
Requires-Dist: requests (>=2.31.0,<3.0.0)
Requires-Dist: rich (>=13.5.2,<14.0.0)
Requires-Dist: tomli (>=2.0.1,<3.0.0)
